adb.py
main_adb-1.0.dist-info/METADATA
main_adb-1.0.dist-info/WHEEL
main_adb-1.0.dist-info/top_level.txt
main_adb-1.0.dist-info/RECORD
